iScore/__init__.py
iScore/__version__.py
iScore/energetic/__init__.py
iScore/energetic/energy.py
iScore/energetic/haddock_energy.py
iScore/energetic/internal_energy.py
iScore/energetic/forcefield/patch.top
iScore/energetic/forcefield/protein-allhdg5-4_new.param
iScore/energetic/forcefield/protein-allhdg5-4_new.top
iScore/function/__init__.py
iScore/function/score.py
iScore/graphrank/__init__.py
iScore/graphrank/graph.py
iScore/graphrank/kernel.py
iScore/graphrank/process.py
iScore/graphrank/rank.py
iScore/graphrank/cuda/Makefile
iScore/graphrank/cuda/cuda_kernel.cu
iScore/graphrank/cuda/kernel.hpp
iScore/graphrank/cuda/main.cu
iScore/h5x/__init__.py
iScore/h5x/baseimport.py
iScore/h5x/menu.py
iScore/model/training_set.tar.gz
iScore/process/__init__.py
iScore/process/plot.py
iScore-0.3.5.data/scripts/iScore.graph
iScore-0.3.5.data/scripts/iScore.graph.mpi
iScore-0.3.5.data/scripts/iScore.h5x
iScore-0.3.5.data/scripts/iScore.kernel
iScore-0.3.5.data/scripts/iScore.kernel.mpi
iScore-0.3.5.data/scripts/iScore.predict
iScore-0.3.5.data/scripts/iScore.predict.mpi
iScore-0.3.5.data/scripts/iScore.svm
iScore-0.3.5.data/scripts/iScore.train
iScore-0.3.5.data/scripts/iScore.train.mpi
iScore-0.3.5.dist-info/LICENSE
iScore-0.3.5.dist-info/METADATA
iScore-0.3.5.dist-info/WHEEL
iScore-0.3.5.dist-info/top_level.txt
iScore-0.3.5.dist-info/RECORD
