Metadata-Version: 2.1
Name: iScore
Version: 0.3.5
Summary: Scoring protein-protein interface using RWGK and SVM
Home-page: https://github.com/DeepRank/iScore
Author: ['Nicolas Renaud', 'Cunliang Geng, Li Xue']
Author-email: n.renaud@esciencecenter.nl
License: Apache Software License 2.0
Keywords: iScore
Platform: UNKNOWN
Classifier: Development Status :: 2 - Pre-Alpha
Classifier: Intended Audience :: Developers
Classifier: License :: OSI Approved :: Apache Software License
Classifier: Natural Language :: English
Classifier: Intended Audience :: Science/Research
Classifier: Programming Language :: Python :: 3.7
Classifier: Topic :: Scientific/Engineering :: Bio-Informatics
License-File: LICENSE
Requires-Dist: numpy (>=1.13)
Requires-Dist: scipy
Requires-Dist: biopython
Requires-Dist: mpi4py
Requires-Dist: h5py
Requires-Dist: matplotlib
Requires-Dist: libsvm
Requires-Dist: pdb2sql
Requires-Dist: pssmgen
Requires-Dist: h5xplorer ; platform_system == "Darwin"
Provides-Extra: dev
Requires-Dist: prospector[with_pyroma] ; extra == 'dev'
Requires-Dist: yapf ; extra == 'dev'
Requires-Dist: isort ; extra == 'dev'
Provides-Extra: doc
Requires-Dist: recommonmark ; extra == 'doc'
Requires-Dist: sphinx ; extra == 'doc'
Requires-Dist: sphinx-rtd-theme ; extra == 'doc'
Provides-Extra: test
Requires-Dist: pytest ; extra == 'test'
Requires-Dist: pytest-cov ; extra == 'test'
Requires-Dist: coveralls ; extra == 'test'
